kmpc/__init__.py
kmpc/command_line.py
kmpc/extra.py
kmpc/kmpcapp.py
kmpc/kmpccache.py
kmpc/kmpcmongo.py
kmpc/library.py
kmpc/mpdfactory.py
kmpc/nowplaying.py
kmpc/queue.py
kmpc/ratingssync.py
kmpc/screenmanager.py
kmpc/sync.py
kmpc/system.py
kmpc/version.py
kmpc/widgets.py
kmpc/resources/fonts/DejaVuSans-Bold.ttf
kmpc/resources/fonts/DejaVuSans.ttf
kmpc/resources/fonts/FontAwesome.ttf
kmpc/resources/images/backdrop.png
kmpc/resources/images/button-down.png
kmpc/resources/images/button-normal.png
kmpc/resources/images/clear.png
kmpc/resources/images/list-backdrop.png
kmpc/resources/images/track-slider-cursor.png
kmpc/resources/json/config_colors.json
kmpc/resources/json/config_mpd.json
kmpc/resources/json/config_paths.json
kmpc/resources/json/config_star.json
kmpc/resources/json/config_sync.json
kmpc/resources/json/config_system.json
kmpc/resources/kv/library.kv
kmpc/resources/kv/nowplaying.kv
kmpc/resources/kv/queue.kv
kmpc/resources/kv/screenmanager.kv
kmpc/resources/kv/system.kv
kmpc/resources/kv/widgets.kv
kmpc-0.7.1.dist-info/LICENSE.txt
kmpc-0.7.1.dist-info/METADATA
kmpc-0.7.1.dist-info/WHEEL
kmpc-0.7.1.dist-info/entry_points.txt
kmpc-0.7.1.dist-info/top_level.txt
kmpc-0.7.1.dist-info/RECORD
